{
   "type": "FeatureCollection",
   "features": [
  {
    "type": "Feature",
    "geometry": {
       "type": "Point",
       "coordinates":  [ 121.4985894,25.03444276 ]
    },
    "properties": {
    "類型":"民間團體",
    "服務單位名稱":"財團法人創世社會福利基金會萬\n華平安站",
    "供餐時間":"週一至週五",
    "地址":"臺北市萬華區大理街 89 號",
    "電話":"(02)2336-1247"
    }
  },
  {
    "type": "Feature",
    "geometry": {
       "type": "Point",
       "coordinates":  [ 121.5157159,25.05983704 ]
    },
    "properties": {
    "類型":"民間團體",
    "服務單位名稱":"財團法人基督教救世軍臺北街友\n關懷中心",
    "供餐時間":"週一至週四中午、週五傍晚",
    "地址":"臺北市大同區錦西街 65 巷\n42 號",
    "電話":"(02)2552-0536"
    }
  },
  {
    "type": "Feature",
    "geometry": {
       "type": "Point",
       "coordinates":  [ 121.520668,25.04907498 ]
    },
    "properties": {
    "類型":"民間團體",
    "服務單位名稱":"財團法人中華民\n國恩友愛心協會臺北恩友中心",
    "供餐時間":"週二至週日",
    "地址":"臺北市中山區華陰街 3-1 號",
    "電話":"(02)2542-8394"
    }
  },
  {
    "type": "Feature",
    "geometry": {
       "type": "Point",
       "coordinates":  [ 121.6068286,25.0546698 ]
    },
    "properties": {
    "類型":"民間團體",
    "服務單位名稱":"財團法人中華民國恩友愛心協會\n南港恩友中心",
    "供餐時間":"週日中午",
    "地址":"臺北市南港區忠孝東路 7 段\n547 號",
    "電話":"(02)2782-4078"
    }
  }
]
}